redbee_mcp/__init__.py
redbee_mcp/__main__.py
redbee_mcp/cli.py
redbee_mcp/client.py
redbee_mcp/handler.py
redbee_mcp/http_server.py
redbee_mcp/models.py
redbee_mcp/py.typed
redbee_mcp/server.py
redbee_mcp/tools/__init__.py
redbee_mcp/tools/auth.py
redbee_mcp/tools/content.py
redbee_mcp/tools/purchases.py
redbee_mcp/tools/system.py
redbee_mcp/tools/user_management.py
redbee_mcp-1.4.2.dist-info/licenses/LICENSE
redbee_mcp-1.4.2.dist-info/METADATA
redbee_mcp-1.4.2.dist-info/WHEEL
redbee_mcp-1.4.2.dist-info/entry_points.txt
redbee_mcp-1.4.2.dist-info/top_level.txt
redbee_mcp-1.4.2.dist-info/RECORD
