Metadata-Version: 2.4
Name: redbee-mcp
Version: 1.4.2
Summary: MCP Server for Red Bee Media OTT Platform - MCP Interface for Exposure APIs
Author-email: Tamsi Besson <tamsi.besson@gmail.com>
License-Expression: MIT
Project-URL: Homepage, https://github.com/tamsibesson/redbee-mcp
Project-URL: Documentation, https://github.com/tamsibesson/redbee-mcp#readme
Project-URL: Repository, https://github.com/tamsibesson/redbee-mcp.git
Project-URL: Bug Tracker, https://github.com/tamsibesson/redbee-mcp/issues
Project-URL: Red Bee Media, https://www.redbeemedia.com/
Keywords: mcp,model-context-protocol,redbee,media,ott,streaming,api
Classifier: Development Status :: 4 - Beta
Classifier: Intended Audience :: Developers
Classifier: Programming Language :: Python :: 3
Classifier: Programming Language :: Python :: 3.8
Classifier: Programming Language :: Python :: 3.9
Classifier: Programming Language :: Python :: 3.10
Classifier: Programming Language :: Python :: 3.11
Classifier: Programming Language :: Python :: 3.12
Classifier: Topic :: Software Development :: Libraries :: Python Modules
Classifier: Topic :: Communications
Classifier: Topic :: Multimedia :: Video
Classifier: Operating System :: OS Independent
Requires-Python: >=3.8
License-File: LICENSE
Requires-Dist: mcp>=1.0.0
Requires-Dist: aiohttp>=3.8.0
Requires-Dist: pydantic>=2.0.0
Requires-Dist: httpx>=0.25.0
Requires-Dist: fastapi>=0.104.0
Requires-Dist: uvicorn>=0.24.0
Provides-Extra: dev
Requires-Dist: pytest>=7.0.0; extra == "dev"
Requires-Dist: pytest-asyncio>=0.21.0; extra == "dev"
Requires-Dist: black>=22.0.0; extra == "dev"
Requires-Dist: isort>=5.10.0; extra == "dev"
Requires-Dist: flake8>=5.0.0; extra == "dev"
Requires-Dist: mypy>=1.0.0; extra == "dev"
Dynamic: license-file
